MANIFEST.in
setup.py
Ragool/__init__.py
Ragool/ragool-template.html
Ragool/ragool.py
Ragool/ragool_view.py
ragool.egg-info/PKG-INFO
ragool.egg-info/SOURCES.txt
ragool.egg-info/dependency_links.txt
ragool.egg-info/not-zip-safe
ragool.egg-info/requires.txt
ragool.egg-info/top_level.txt