Metadata-Version: 1.1
Name: ragool
Version: 0.0.1b
Summary: Handle Bottle.py errors with love <3
Home-page: https://github.com/aybb/ragool
Author: aybb
Author-email: lasthitknxx@gmail.com
License: MIT
Keywords: error handling
Platform: UNKNOWN
Classifier: Development Status :: 3 - Alpha
Classifier: License :: OSI Approved :: MIT License
Classifier: Programming Language :: Python :: 3.4
Classifier: Framework :: Bottle
Classifier: Topic :: Utilities
